hwscheduler/__init__.py
hwscheduler/huawei/__init__.py
hwscheduler/huawei/config_pwdless.py
hwscheduler/huawei/deleteServer.py
hwscheduler/huawei/ecs_manager.py
hwscheduler/huawei/eip_manager.py
hwscheduler/huawei/fabric_login.py
hwscheduler/huawei/saveInfo.py
hwscheduler/huawei/test_build_chukonu.py
hwscheduler/huawei/test_spark_base.py
hwscheduler/huawei/test_start_runner.py
hwscheduler/tasks/__init__.py
hwscheduler/tasks/line.py
hwscheduler/tasks/task_build_chukonu.py
hwscheduler/tasks/task_build_wheel.py
hwscheduler/tasks/task_spark_base.py
hwscheduler/tasks/task_spark_base2.py
hwscheduler/tasks/task_start_runner.py
hwscheduler/tasks/task_unitest_base.py
hwscheduler/utils/__init__.py
hwscheduler/utils/logging.py
hwscheduler-0.6.1.dist-info/METADATA
hwscheduler-0.6.1.dist-info/WHEEL
hwscheduler-0.6.1.dist-info/top_level.txt
hwscheduler-0.6.1.dist-info/RECORD
