Metadata-Version: 2.4
Name: hwscheduler
Version: 0.6.1
Requires-Python: >=3.6
Requires-Dist: huaweicloudsdkcore==3.1.149
Requires-Dist: huaweicloudsdkecs==3.1.149
Requires-Dist: huaweicloudsdkeip==3.1.149
Requires-Dist: fabric==3.2.2
Requires-Dist: rich==14.0.0
Dynamic: requires-dist
Dynamic: requires-python
